casa6_install/__init__.py
casa6_install/casa6_install.py
casa6_install-1.1.4.dist-info/LICENSE
casa6_install-1.1.4.dist-info/METADATA
casa6_install-1.1.4.dist-info/WHEEL
casa6_install-1.1.4.dist-info/entry_points.txt
casa6_install-1.1.4.dist-info/top_level.txt
casa6_install-1.1.4.dist-info/RECORD
