Metadata-Version: 2.1
Name: casa6-install
Version: 1.1.4
Summary: UNKNOWN
Home-page: https://github.com/r-xue/casa6-docker
Author: Rui Xue
Author-email: rx.astro@gmail.com
License: BSD license
Project-URL: Bug Reports, https://github.com/r-xue/casa-docker/issues
Project-URL: Source, https://github.com/r-xue/casa-docker
Keywords: casa6,Docker,Singularity
Platform: UNKNOWN
Classifier: Intended Audience :: Developers
Classifier: License :: OSI Approved :: BSD License
Classifier: Natural Language :: English
Classifier: Programming Language :: Python :: 3.7
Classifier: Programming Language :: Python :: 3.8
Requires-Python: >=3.7
Requires-Dist: pip (>20.0)
Requires-Dist: wheel (>=0.35.1)
